[
    {
        "actionName": "Action",
        "steps": [
            {
                "stepId": "STEP36",
                "stepName": "Url: WebTours",
                "infFile": "t1.inf",
                "time": 1662038197604
            },
            {
                "stepId": "STEP37",
                "stepName": "Link: sign up now",
                "infFile": "t2.inf",
                "time": 1662038197712
            },
            {
                "stepId": "STEP38",
                "stepName": "Submit Form: login.pl",
                "infFile": "t3.inf",
                "time": 1662038197805
            },
            {
                "stepId": "STEP39",
                "stepName": "Image: button_next.gif",
                "infFile": "t4.inf",
                "time": 1662038197963
            },
            {
                "stepId": "STEP40",
                "stepName": "Image: SignOff Button",
                "infFile": "t5.inf",
                "time": 1662038198101
            }
        ],
        "transactions": [
            {
                "transactionName": "NewUserRegistration",
                "rawStartTime": 1662038197627,
                "rawEndTime": 1662038197816,
                "thinkTime": 0.0,
                "wastedTime": 0.043749332427978519
            },
            {
                "transactionName": "ContinueAfterRegistration",
                "rawStartTime": 1662038197827,
                "rawEndTime": 1662038197974,
                "thinkTime": 0.0,
                "wastedTime": 0.021677494049072267
            },
            {
                "transactionName": "logout",
                "rawStartTime": 1662038197985,
                "rawEndTime": 1662038198112,
                "thinkTime": 0.0,
                "wastedTime": 0.020647048950195314
            },
            {
                "transactionName": "AUX_AddingUsersToWebTours",
                "rawStartTime": 1662038197493,
                "rawEndTime": 1662038198123,
                "thinkTime": 0.0,
                "wastedTime": 0.10765290260314942
            }
        ]
    }
]